APB/slave.sv
`timescale 1ns / 1ns

module slave (
    input PCLK,         // Clock signal
    PRESETn,            // Active-low reset signal
    input PSEL,         // Peripheral select signal
    PENABLE,            // Enable signal for APB transaction
    PWRITE,             // Read (0) or Write (1) control signal
    input [7:0] PADDR,  // Address bus
    PWDATA,             // Write data bus
    output [7:0] PRDATA, // Read data bus
    output reg PREADY    // Ready signal
);

  reg [7:0] reg_addr;    // Register to store address for read operation
  reg [7:0] mem[0:63];   // Memory array of 64 locations (8-bit each)

  // Assign output read data from memory
  assign PRDATA = mem[reg_addr];

  // APB Slave behavior based on PSEL, PENABLE, and PWRITE signals
  always @(*) begin
    if (!PRESETn) PREADY = 0; // Reset condition
    
    // Setup phase (Read operation): Address is latched
    else if (PSEL && !PENABLE && !PWRITE) begin
      PREADY = 0;
    end 
    
    // Enable phase (Read operation): Provide read data
    else if (PSEL && PENABLE && !PWRITE) begin
      PREADY   = 1;
      reg_addr = PADDR;
    end 
    
    // Setup phase (Write operation): Address and data setup
    else if (PSEL && !PENABLE && PWRITE) begin
      PREADY = 0;
    end 
    
    // Enable phase (Write operation): Write data to memory
    else if (PSEL && PENABLE && PWRITE) begin
      PREADY = 1;
      mem[PADDR] = PWDATA;
    end 
    
    else PREADY = 0; // Default case: Not ready
  end
endmodule

APB/master.sv
`timescale 1ns / 1ns

module master_bridge (
    input [8:0] apb_write_paddr, // Write address for APB bus
    apb_read_paddr,             // Read address for APB bus
    input [7:0] apb_write_data, // Data to be written to APB bus
    PRDATA,                     // Data read from APB bus
    input PRESETn,              // Active-low reset signal
    PCLK,                       // Clock signal
    READ_WRITE,                 // Read (1) or Write (0) control signal
    transfer,                   // Transfer enable signal
    PREADY,                     // Peripheral ready signal
    output PSEL1, PSEL2,        // Peripheral select signals
    output reg PENABLE,         // Enable signal for APB transaction
    output reg [8:0] PADDR,     // APB address bus
    output reg PWRITE,          // Write enable signal
    output reg [7:0] PWDATA,    // Data to be written
    apb_read_data_out,          // Output for read data
    output PSLVERR              // Slave error flag
);

  // State registers
  reg [2:0] state, next_state;
  reg invalid_setup_error, setup_error, invalid_read_paddr, invalid_write_paddr, invalid_write_data;
  
  // FSM State Encoding
  parameter IDLE = 3'b001, SETUP = 3'b010, ENABLE = 3'b100;

  // Sequential logic: State transition
  always @(posedge PCLK) begin
    if (!PRESETn) state <= IDLE; // Reset to IDLE state
    else state <= next_state;
  end

  // Combinational logic: Next state logic and output control
  always @(state, transfer, PREADY) begin
    if (!PRESETn) next_state = IDLE;
    else begin
      PWRITE = ~READ_WRITE; // Determine read/write operation
      case (state)

        IDLE: begin
          PENABLE = 0;
          if (!transfer) next_state = IDLE;
          else next_state = SETUP;
        end

        SETUP: begin
          PENABLE = 0;
          if (READ_WRITE) PADDR = apb_read_paddr; // Load read address
          else begin
            PADDR  = apb_write_paddr; // Load write address
            PWDATA = apb_write_data;  // Load write data
          end
          
          if (transfer && !PSLVERR) next_state = ENABLE;
          else next_state = IDLE;
        end

        ENABLE: begin
          if (PSEL1 || PSEL2) PENABLE = 1; // Enable APB transaction
          
          if (transfer & !PSLVERR) begin
            if (PREADY) begin
              if (!READ_WRITE) next_state = SETUP; // Continue writing
              else begin
                next_state = SETUP;
                apb_read_data_out = PRDATA; // Store read data
              end
            end else next_state = ENABLE; // Wait for PREADY
          end else next_state = IDLE;
        end

        default: next_state = IDLE;
      endcase
    end
  end

  // Assign peripheral select signals based on address
  assign {PSEL1, PSEL2} = ((state != IDLE) ? (PADDR[8] ? {1'b0, 1'b1} : {1'b1, 1'b0}) : 2'd0);

  // Error detection logic
  always @(*) begin
    if (!PRESETn) begin
      setup_error = 0;
      invalid_read_paddr = 0;
      invalid_write_paddr = 0;
      invalid_write_data = 0;
    end else begin
      if (state == IDLE && next_state == ENABLE) setup_error = 1;
      else setup_error = 0;
      
      if ((apb_write_data === 8'dx) && (!READ_WRITE) && (state == SETUP || state == ENABLE))
        invalid_write_data = 1;
      else invalid_write_data = 0;
      
      if ((apb_read_paddr === 9'dx) && READ_WRITE && (state == SETUP || state == ENABLE))
        invalid_read_paddr = 1;
      else invalid_read_paddr = 0;
      
      if ((apb_write_paddr === 9'dx) && (!READ_WRITE) && (state == SETUP || state == ENABLE))
        invalid_write_paddr = 1;
      else invalid_write_paddr = 0;
      
      if (state == SETUP) begin
        if (PWRITE) begin
          if (PADDR == apb_write_paddr && PWDATA == apb_write_data) setup_error = 1'b0;
          else setup_error = 1'b1;
        end else begin
          if (PADDR == apb_read_paddr) setup_error = 1'b0;
          else setup_error = 1'b1;
        end
      end else setup_error = 1'b0;
    end
    
    // Generate overall error flag
    invalid_setup_error = setup_error || invalid_read_paddr || invalid_write_data || invalid_write_paddr;
  end

  assign PSLVERR = invalid_setup_error; // Assign error signal

endmodule

APB/apb_top.sv
`timescale 1ns / 1ns

`include "master.sv" // Include Master Bridge module
`include "slave.sv"  // Include Slave module

module APB_Protocol (
    input PCLK,             // Clock signal
    PRESETn,                // Active-low reset signal
    transfer,               // Transfer enable signal
    READ_WRITE,             // Read (1) or Write (0) control signal
    input [8:0] apb_write_paddr, // APB write address
    input [7:0] apb_write_data,  // Data to be written
    input [8:0] apb_read_paddr,  // APB read address
    output PSLVERR,         // Slave error signal
    output [7:0] apb_read_data_out // Read data output
);

  // Internal signals
  wire [7:0] PWDATA, PRDATA, PRDATA1, PRDATA2; // Data buses
  wire [8:0] PADDR; // Address bus

  wire PREADY, PREADY1, PREADY2, PENABLE, PSEL1, PSEL2, PWRITE; // Control signals

  // Select appropriate ready signal based on address MSB
  assign PREADY = PADDR[8] ? PREADY2 : PREADY1;
  
  // Select appropriate read data based on address MSB when READ_WRITE is asserted
  assign PRDATA = READ_WRITE ? (PADDR[8] ? PRDATA2 : PRDATA1) : 8'dx;

  // Instantiate the Master Bridge module
  master_bridge dut_mas (
    apb_write_paddr,   // Write address
    apb_read_paddr,    // Read address
    apb_write_data,    // Write data
    PRDATA,            // Read data
    PRESETn,           // Reset signal
    PCLK,              // Clock signal
    READ_WRITE,        // Read/Write control
    transfer,          // Transfer enable
    PREADY,            // Ready signal
    PSEL1,             // Select signal for Slave 1
    PSEL2,             // Select signal for Slave 2
    PENABLE,           // Enable signal
    PADDR,             // Address bus
    PWRITE,            // Write enable signal
    PWDATA,            // Write data bus
    apb_read_data_out, // Read data output
    PSLVERR            // Slave error signal
  );

  // Instantiate Slave 1
  slave dut1 (
    PCLK,          // Clock signal
    PRESETn,       // Reset signal
    PSEL1,         // Select signal for Slave 1
    PENABLE,       // Enable signal
    PWRITE,        // Write enable signal
    PADDR[7:0],    // Address bus (lower 8 bits)
    PWDATA,        // Write data bus
    PRDATA1,       // Read data output
    PREADY1        // Ready signal
  );

  // Instantiate Slave 2
  slave dut2 (
    PCLK,          // Clock signal
    PRESETn,       // Reset signal
    PSEL2,         // Select signal for Slave 2
    PENABLE,       // Enable signal
    PWRITE,        // Write enable signal
    PADDR[7:0],    // Address bus (lower 8 bits)
    PWDATA,        // Write data bus
    PRDATA2,       // Read data output
    PREADY2        // Ready signal
  );

endmodule

APB/test.sv
`timescale 1ns / 1ns
`include "apb_top.sv" // Include the APB Protocol module

module test;

  // Declare testbench signals
  reg PCLK, PRESETn, transfer, READ_WRITE;
  reg [8:0] apb_write_paddr;
  reg [7:0] apb_write_data;
  reg [8:0] apb_read_paddr;
  wire [7:0] apb_read_data_out;
  wire PSLVERR;
  reg [7:0] data, expected;

  // Instantiate the APB Protocol module
  APB_Protocol dut_c (
      PCLK,
      PRESETn,
      transfer,
      READ_WRITE,
      apb_write_paddr,
      apb_write_data,
      apb_read_paddr,
      PSLVERR,
      apb_read_data_out
  );

  integer i, j;

  // Generate clock signal with 10ns period
  initial begin
    PCLK <= 0;
    forever #5 PCLK = ~PCLK;
  end

  initial begin
    // Initialize signals
    PRESETn  <= 0;
    transfer <= 0;
    READ_WRITE = 0;
    apb_write_paddr = 0;
    apb_write_data = 0;
    apb_read_paddr = 0;

    // Apply reset
    @(posedge PCLK) PRESETn = 1;
    
    // No write address available but request for write operation
    @(posedge PCLK) transfer = 1;
    repeat (2) @(posedge PCLK);
    @(negedge PCLK) Write_slave1;  // Perform write operation to slave 1

    repeat (3) @(posedge PCLK);
    Write_slave2;  // Perform write operation to slave 2

    @(posedge PCLK);
    apb_write_paddr = 9'd526;
    apb_write_data  = 9'd9;
    repeat (2) @(posedge PCLK);
    apb_write_paddr = 9'd22;
    apb_write_data  = 9'd35;
    repeat (2) @(posedge PCLK);
    
    // Initiate read operations
    @(posedge PCLK) READ_WRITE = 1;
    PRESETn  <= 0;
    transfer <= 0;
    @(posedge PCLK) PRESETn = 1;
    
    repeat (3) @(posedge PCLK) transfer = 1;  // No read address available but request for read operation
    repeat (2) @(posedge PCLK) Read_slave1;  // Perform read operation from slave 1

    repeat (3) @(posedge PCLK);
    Read_slave2;  // Perform read operation from slave 2

    repeat (3) @(posedge PCLK);
    apb_read_paddr = 9'd45;  // Request read operation from an address not written to
    repeat (4) @(posedge PCLK);
    $finish;
  end

  // Task to write data to Slave 1
  task Write_slave1;
    begin
      transfer = 1;
      for (i = 0; i < 8; i = i + 1) begin
        repeat (2)
          @(negedge PCLK) begin
            data = i;
            apb_write_data = 2 * i;
            apb_write_paddr = {1'b0, data};
          end
      end
    end
  endtask

  // Task to write data to Slave 2
  task Write_slave2;
    begin
      for (i = 0; i < 8; i = i + 1) begin
        repeat (2)
          @(negedge PCLK) begin
            data = i;
            apb_write_paddr = {1'b1, data};
            apb_write_data = i;
          end
      end
    end
  endtask

  // Task to read data from Slave 1
  task Read_slave1;
    begin
      for (j = 0; j < 8; j = j + 1) begin
        repeat (2)
          @(negedge PCLK) begin
            data = j;
            apb_read_paddr = {1'b0, data};
          end
      end
    end
  endtask

  // Task to read data from Slave 2
  task Read_slave2;
    begin
      for (j = 0; j < 8; j = j + 1) begin
        repeat (2)
          @(negedge PCLK) begin
            data = j;
            apb_read_paddr = {1'b1, data};
          end
      end
    end
  endtask

  // Dump waveform for simulation
  initial begin
    $dumpfile("dump.vcd");
    $dumpvars;
  end

endmodule

build/apbWaveform.vcd
$date
	Wed Mar 26 21:07:28 2025
$end
$version
	Icarus Verilog
$end
$timescale
	1ns
$end
$scope module test $end
$var wire 8 ! apb_read_data_out [7:0] $end
$var wire 1 " PSLVERR $end
$var reg 1 # PCLK $end
$var reg 1 $ PRESETn $end
$var reg 1 % READ_WRITE $end
$var reg 9 & apb_read_paddr [8:0] $end
$var reg 8 ' apb_write_data [7:0] $end
$var reg 9 ( apb_write_paddr [8:0] $end
$var reg 8 ) data [7:0] $end
$var reg 1 * transfer $end
$var integer 32 + i [31:0] $end
$var integer 32 , j [31:0] $end
$scope module dut_c $end
$var wire 1 # PCLK $end
$var wire 1 $ PRESETn $end
$var wire 1 % READ_WRITE $end
$var wire 9 - apb_read_paddr [8:0] $end
$var wire 8 . apb_write_data [7:0] $end
$var wire 9 / apb_write_paddr [8:0] $end
$var wire 1 * transfer $end
$var wire 8 0 apb_read_data_out [7:0] $end
$var wire 1 1 PWRITE $end
$var wire 8 2 PWDATA [7:0] $end
$var wire 1 " PSLVERR $end
$var wire 1 3 PSEL2 $end
$var wire 1 4 PSEL1 $end
$var wire 1 5 PREADY2 $end
$var wire 1 6 PREADY1 $end
$var wire 1 7 PREADY $end
$var wire 8 8 PRDATA2 [7:0] $end
$var wire 8 9 PRDATA1 [7:0] $end
$var wire 8 : PRDATA [7:0] $end
$var wire 1 ; PENABLE $end
$var wire 9 < PADDR [8:0] $end
$scope module dut1 $end
$var wire 8 = PADDR [7:0] $end
$var wire 1 # PCLK $end
$var wire 8 > PRDATA [7:0] $end
$var wire 1 $ PRESETn $end
$var wire 1 1 PWRITE $end
$var wire 8 ? PWDATA [7:0] $end
$var wire 1 4 PSEL $end
$var wire 1 ; PENABLE $end
$var reg 1 6 PREADY $end
$var reg 8 @ reg_addr [7:0] $end
$upscope $end
$scope module dut2 $end
$var wire 8 A PADDR [7:0] $end
$var wire 1 # PCLK $end
$var wire 8 B PRDATA [7:0] $end
$var wire 1 $ PRESETn $end
$var wire 1 1 PWRITE $end
$var wire 8 C PWDATA [7:0] $end
$var wire 1 3 PSEL $end
$var wire 1 ; PENABLE $end
$var reg 1 5 PREADY $end
$var reg 8 D reg_addr [7:0] $end
$upscope $end
$scope module dut_mas $end
$var wire 1 # PCLK $end
$var wire 8 E PRDATA [7:0] $end
$var wire 1 7 PREADY $end
$var wire 1 $ PRESETn $end
$var wire 1 " PSLVERR $end
$var wire 1 % READ_WRITE $end
$var wire 9 F apb_read_paddr [8:0] $end
$var wire 8 G apb_write_data [7:0] $end
$var wire 9 H apb_write_paddr [8:0] $end
$var wire 1 * transfer $end
$var wire 1 3 PSEL2 $end
$var wire 1 4 PSEL1 $end
$var parameter 3 I ENABLE $end
$var parameter 3 J IDLE $end
$var parameter 3 K SETUP $end
$var reg 9 L PADDR [8:0] $end
$var reg 1 ; PENABLE $end
$var reg 8 M PWDATA [7:0] $end
$var reg 1 1 PWRITE $end
$var reg 8 N apb_read_data_out [7:0] $end
$var reg 1 O invalid_read_paddr $end
$var reg 1 P invalid_setup_error $end
$var reg 1 Q invalid_write_data $end
$var reg 1 R invalid_write_paddr $end
$var reg 3 S next_state [2:0] $end
$var reg 1 T setup_error $end
$var reg 3 U state [2:0] $end
$upscope $end
$upscope $end
$scope task Read_slave1 $end
$upscope $end
$scope task Read_slave2 $end
$upscope $end
$scope task Write_slave1 $end
$upscope $end
$scope task Write_slave2 $end
$upscope $end
$upscope $end
$enddefinitions $end
$comment Show the parameter values. $end
$dumpall
b10 K
b1 J
b100 I
$end
#0
$dumpvars
bx U
0T
b1 S
0R
0Q
0P
0O
bx N
bx M
bx L
b0 H
b0 G
b0 F
bx E
bx D
bx C
bx B
bx A
bx @
bx ?
bx >
bx =
bx <
x;
bx :
bx 9
bx 8
07
06
05
x4
x3
bx 2
11
bx 0
b0 /
b0 .
b0 -
bx ,
bx +
0*
bx )
b0 (
b0 '
b0 &
0%
0$
0#
0"
bx !
$end
#5
03
04
0;
b1 U
1$
1#
#10
0#
#15
b10 S
1*
1#
#20
0#
#25
b0 A
b0 =
03
14
b100 S
b0 2
b0 ?
b0 C
b0 M
b0 <
b0 L
b10 U
1#
#30
0#
#35
b10 S
17
16
1;
b100 U
1#
#40
b0 +
0#
#45
07
06
b100 S
0;
b10 U
1#
#50
b0 )
0#
#55
b10 S
17
16
1;
b100 U
1#
#60
b1 +
0#
#65
07
06
b100 S
0;
b10 U
1#
#70
1"
1P
1T
b1 (
b1 /
b1 H
b10 '
b10 .
b10 G
b1 )
0#
#75
17
16
0"
0P
0T
b10 S
1;
b100 U
1#
#80
b10 +
0#
#85
07
b1 A
b1 =
06
b100 S
b10 2
b10 ?
b10 C
b10 M
b1 <
b1 L
0;
b10 U
1#
#90
1"
1P
1T
b10 (
b10 /
b10 H
b100 '
b100 .
b100 G
b10 )
0#
#95
17
16
0"
0P
0T
b10 S
1;
b100 U
1#
#100
b11 +
0#
#105
07
b10 A
b10 =
06
b100 S
b100 2
b100 ?
b100 C
b100 M
b10 <
b10 L
0;
b10 U
1#
#110
1"
1P
1T
b11 (
b11 /
b11 H
b110 '
b110 .
b110 G
b11 )
0#
#115
17
16
0"
0P
0T
b10 S
1;
b100 U
1#
#120
b100 +
0#
#125
07
b11 A
b11 =
06
b100 S
b110 2
b110 ?
b110 C
b110 M
b11 <
b11 L
0;
b10 U
1#
#130
1"
1P
1T
b100 (
b100 /
b100 H
b1000 '
b1000 .
b1000 G
b100 )
0#
#135
17
16
0"
0P
0T
b10 S
1;
b100 U
1#
#140
b101 +
0#
#145
07
b100 A
b100 =
06
b100 S
b1000 2
b1000 ?
b1000 C
b1000 M
b100 <
b100 L
0;
b10 U
1#
#150
1"
1P
1T
b101 (
b101 /
b101 H
b1010 '
b1010 .
b1010 G
b101 )
0#
#155
17
16
0"
0P
0T
b10 S
1;
b100 U
1#
#160
b110 +
0#
#165
07
b101 A
b101 =
06
b100 S
b1010 2
b1010 ?
b1010 C
b1010 M
b101 <
b101 L
0;
b10 U
1#
#170
1"
1P
1T
b110 (
b110 /
b110 H
b1100 '
b1100 .
b1100 G
b110 )
0#
#175
17
16
0"
0P
0T
b10 S
1;
b100 U
1#
#180
b111 +
0#
#185
07
b110 A
b110 =
06
b100 S
b1100 2
b1100 ?
b1100 C
b1100 M
b110 <
b110 L
0;
b10 U
1#
#190
1"
1P
1T
b111 (
b111 /
b111 H
b1110 '
b1110 .
b1110 G
b111 )
0#
#195
17
16
0"
0P
0T
b10 S
1;
b100 U
1#
#200
b1000 +
0#
#205
07
b111 A
b111 =
06
b100 S
b1110 2
b1110 ?
b1110 C
b1110 M
b111 <
b111 L
0;
b10 U
1#
#210
0#
#215
b10 S
17
16
1;
b100 U
1#
#220
0#
#225
07
06
b100 S
0;
b10 U
b0 +
1#
#230
1"
1P
1T
b0 '
b0 .
b0 G
b100000000 (
b100000000 /
b100000000 H
b0 )
0#
#235
17
16
0"
0P
0T
b10 S
1;
b100 U
1#
#240
b1 +
0#
#245
13
04
07
b0 A
b0 =
06
b100 S
b0 2
b0 ?
b0 C
b0 M
b100000000 <
b100000000 L
0;
b10 U
1#
#250
1"
1P
1T
b1 '
b1 .
b1 G
b100000001 (
b100000001 /
b100000001 H
b1 )
0#
#255
17
15
0"
0P
0T
b10 S
1;
b100 U
1#
#260
b10 +
0#
#265
07
b1 A
b1 =
05
b100 S
b1 2
b1 ?
b1 C
b1 M
b100000001 <
b100000001 L
0;
b10 U
1#
#270
1"
1P
1T
b10 '
b10 .
b10 G
b100000010 (
b100000010 /
b100000010 H
b10 )
0#
#275
17
15
0"
0P
0T
b10 S
1;
b100 U
1#
#280
b11 +
0#
#285
07
b10 A
b10 =
05
b100 S
b10 2
b10 ?
b10 C
b10 M
b100000010 <
b100000010 L
0;
b10 U
1#
#290
1"
1P
1T
b11 '
b11 .
b11 G
b100000011 (
b100000011 /
b100000011 H
b11 )
0#
#295
17
15
0"
0P
0T
b10 S
1;
b100 U
1#
#300
b100 +
0#
#305
07
b11 A
b11 =
05
b100 S
b11 2
b11 ?
b11 C
b11 M
b100000011 <
b100000011 L
0;
b10 U
1#
#310
1"
1P
1T
b100 '
b100 .
b100 G
b100000100 (
b100000100 /
b100000100 H
b100 )
0#
#315
17
15
0"
0P
0T
b10 S
1;
b100 U
1#
#320
b101 +
0#
#325
07
b100 A
b100 =
05
b100 S
b100 2
b100 ?
b100 C
b100 M
b100000100 <
b100000100 L
0;
b10 U
1#
#330
1"
1P
1T
b101 '
b101 .
b101 G
b100000101 (
b100000101 /
b100000101 H
b101 )
0#
#335
17
15
0"
0P
0T
b10 S
1;
b100 U
1#
#340
b110 +
0#
#345
07
b101 A
b101 =
05
b100 S
b101 2
b101 ?
b101 C
b101 M
b100000101 <
b100000101 L
0;
b10 U
1#
#350
1"
1P
1T
b110 '
b110 .
b110 G
b100000110 (
b100000110 /
b100000110 H
b110 )
0#
#355
17
15
0"
0P
0T
b10 S
1;
b100 U
1#
#360
b111 +
0#
#365
07
b110 A
b110 =
05
b100 S
b110 2
b110 ?
b110 C
b110 M
b100000110 <
b100000110 L
0;
b10 U
1#
#370
1"
1P
1T
b111 '
b111 .
b111 G
b100000111 (
b100000111 /
b100000111 H
b111 )
0#
#375
17
15
0"
0P
0T
b10 S
1;
b100 U
1#
#380
b1000 +
0#
#385
03
14
07
b1110 A
b1110 =
05
b100 S
b1001 2
b1001 ?
b1001 C
b1001 M
b1110 <
b1110 L
0;
b10 U
b1001 '
b1001 .
b1001 G
b1110 (
b1110 /
b1110 H
1#
#390
0#
#395
b10 S
17
16
1;
b100 U
1#
#400
0#
#405
07
b10110 A
b10110 =
06
b100 S
b100011 2
b100011 ?
b100011 C
b100011 M
b10110 <
b10110 L
0;
b10 U
b100011 '
b100011 .
b100011 G
b10110 (
b10110 /
b10110 H
1#
#410
0#
#415
b10 S
17
16
1;
b100 U
1#
#420
0#
#425
07
06
b100 S
0;
b10 U
1#
#430
0#
#435
b1 S
0*
0$
b100 U
1%
1#
#440
0#
#445
04
01
b1 U
1$
1#
#450
0#
#455
b10 S
1*
1#
#460
0#
#465
b0 A
b0 =
14
b100 S
b0 <
b0 L
b10 U
1#
#470
0#
#475
b0 :
b0 E
b10 S
17
b0 9
b0 >
b0 @
16
1;
b100 U
1#
#480
0#
#485
07
06
b100 S
0;
b10 U
b0 ,
1#
#490
b0 )
0#
#495
b0 !
b0 0
b0 N
b10 S
17
16
1;
b100 U
1#
#500
b1 ,
0#
#505
07
06
b100 S
0;
b10 U
1#
#510
1"
1P
1T
b1 &
b1 -
b1 F
b1 )
0#
#515
17
16
0"
0P
0T
b10 S
1;
b100 U
1#
#520
b10 ,
0#
#525
07
b1 A
b1 =
06
b100 S
b1 <
b1 L
0;
b10 U
1#
#530
1"
1P
1T
b10 &
b10 -
b10 F
b10 )
0#
#535
b10 :
b10 E
17
b10 9
b10 >
b1 @
16
0"
0P
0T
b10 S
1;
b100 U
1#
#540
b11 ,
0#
#545
07
b10 A
b10 =
06
b100 S
b10 <
b10 L
0;
b10 U
1#
#550
1"
1P
1T
b11 &
b11 -
b11 F
b11 )
0#
#555
b100 :
b100 E
b10 !
b10 0
b10 N
17
b100 9
b100 >
b10 @
16
0"
0P
0T
b10 S
1;
b100 U
1#
#560
b100 ,
0#
#565
07
b11 A
b11 =
06
b100 S
b11 <
b11 L
0;
b10 U
1#
#570
1"
1P
1T
b100 &
b100 -
b100 F
b100 )
0#
#575
b110 :
b110 E
b100 !
b100 0
b100 N
17
b110 9
b110 >
b11 @
16
0"
0P
0T
b10 S
1;
b100 U
1#
#580
b101 ,
0#
#585
07
b100 A
b100 =
06
b100 S
b100 <
b100 L
0;
b10 U
1#
#590
1"
1P
1T
b101 &
b101 -
b101 F
b101 )
0#
#595
b1000 :
b1000 E
b110 !
b110 0
b110 N
17
b1000 9
b1000 >
b100 @
16
0"
0P
0T
b10 S
1;
b100 U
1#
#600
b110 ,
0#
#605
07
b101 A
b101 =
06
b100 S
b101 <
b101 L
0;
b10 U
1#
#610
1"
1P
1T
b110 &
b110 -
b110 F
b110 )
0#
#615
b1010 :
b1010 E
b1000 !
b1000 0
b1000 N
17
b1010 9
b1010 >
b101 @
16
0"
0P
0T
b10 S
1;
b100 U
1#
#620
b111 ,
0#
#625
07
b110 A
b110 =
06
b100 S
b110 <
b110 L
0;
b10 U
1#
#630
1"
1P
1T
b111 &
b111 -
b111 F
b111 )
0#
#635
b1100 :
b1100 E
b1010 !
b1010 0
b1010 N
17
b1100 9
b1100 >
b110 @
16
0"
0P
0T
b10 S
1;
b100 U
1#
#640
b1000 ,
0#
#645
07
b111 A
b111 =
06
b100 S
b111 <
b111 L
0;
b10 U
b0 ,
1#
#650
1"
1P
1T
b0 &
b0 -
b0 F
b0 )
0#
#655
b1110 :
b1110 E
b1100 !
b1100 0
b1100 N
17
b1110 9
b1110 >
b111 @
16
0"
0P
0T
b10 S
1;
b100 U
1#
#660
b1 ,
0#
#665
07
b0 A
b0 =
06
b100 S
b0 <
b0 L
0;
b10 U
1#
#670
1"
1P
1T
b1 &
b1 -
b1 F
b1 )
0#
#675
b0 :
b0 E
b1110 !
b1110 0
b1110 N
17
b0 9
b0 >
b0 @
16
0"
0P
0T
b10 S
1;
b100 U
1#
#680
b10 ,
0#
#685
07
b1 A
b1 =
06
b100 S
b1 <
b1 L
0;
b10 U
1#
#690
1"
1P
1T
b10 &
b10 -
b10 F
b10 )
0#
#695
b10 :
b10 E
b0 !
b0 0
b0 N
17
b10 9
b10 >
b1 @
16
0"
0P
0T
b10 S
1;
b100 U
1#
#700
b11 ,
0#
#705
07
b10 A
b10 =
06
b100 S
b10 <
b10 L
0;
b10 U
1#
#710
1"
1P
1T
b11 &
b11 -
b11 F
b11 )
0#
#715
b100 :
b100 E
b10 !
b10 0
b10 N
17
b100 9
b100 >
b10 @
16
0"
0P
0T
b10 S
1;
b100 U
1#
#720
b100 ,
0#
#725
07
b11 A
b11 =
06
b100 S
b11 <
b11 L
0;
b10 U
1#
#730
1"
1P
1T
b100 &
b100 -
b100 F
b100 )
0#
#735
b110 :
b110 E
b100 !
b100 0
b100 N
17
b110 9
b110 >
b11 @
16
0"
0P
0T
b10 S
1;
b100 U
1#
#740
b101 ,
0#
#745
07
b100 A
b100 =
06
b100 S
b100 <
b100 L
0;
b10 U
1#
#750
1"
1P
1T
b101 &
b101 -
b101 F
b101 )
0#
#755
b1000 :
b1000 E
b110 !
b110 0
b110 N
17
b1000 9
b1000 >
b100 @
16
0"
0P
0T
b10 S
1;
b100 U
1#
#760
b110 ,
0#
#765
07
b101 A
b101 =
06
b100 S
b101 <
b101 L
0;
b10 U
1#
#770
1"
1P
1T
b110 &
b110 -
b110 F
b110 )
0#
#775
b1010 :
b1010 E
b1000 !
b1000 0
b1000 N
17
b1010 9
b1010 >
b101 @
16
0"
0P
0T
b10 S
1;
b100 U
1#
#780
b111 ,
0#
#785
07
b110 A
b110 =
06
b100 S
b110 <
b110 L
0;
b10 U
1#
#790
1"
1P
1T
b111 &
b111 -
b111 F
b111 )
0#
#795
b1100 :
b1100 E
b1010 !
b1010 0
b1010 N
17
b1100 9
b1100 >
b110 @
16
0"
0P
0T
b10 S
1;
b100 U
1#
#800
b1000 ,
0#
#805
07
b111 A
b111 =
06
b100 S
b111 <
b111 L
0;
b10 U
1#
#810
0#
#815
b1110 :
b1110 E
b1100 !
b1100 0
b1100 N
b10 S
17
b1110 9
b1110 >
b111 @
16
1;
b100 U
1#
#820
0#
#825
07
06
b100 S
0;
b10 U
b0 ,
1#
#830
1"
1P
1T
b100000000 &
b100000000 -
b100000000 F
b0 )
0#
#835
b1110 !
b1110 0
b1110 N
17
16
0"
0P
0T
b10 S
1;
b100 U
1#
#840
b1 ,
0#
#845
13
04
bx :
bx E
07
b0 A
b0 =
06
b100 S
b100000000 <
b100000000 L
0;
b10 U
1#
#850
1"
1P
1T
b100000001 &
b100000001 -
b100000001 F
b1 )
0#
#855
b0 :
b0 E
bx !
bx 0
bx N
17
b0 8
b0 B
b0 D
15
0"
0P
0T
b10 S
1;
b100 U
1#
#860
b10 ,
0#
#865
07
b1 A
b1 =
05
b100 S
b100000001 <
b100000001 L
0;
b10 U
1#
#870
1"
1P
1T
b100000010 &
b100000010 -
b100000010 F
b10 )
0#
#875
b1 :
b1 E
b0 !
b0 0
b0 N
17
b1 8
b1 B
b1 D
15
0"
0P
0T
b10 S
1;
b100 U
1#
#880
b11 ,
0#
#885
07
b10 A
b10 =
05
b100 S
b100000010 <
b100000010 L
0;
b10 U
1#
#890
1"
1P
1T
b100000011 &
b100000011 -
b100000011 F
b11 )
0#
#895
b10 :
b10 E
b1 !
b1 0
b1 N
17
b10 8
b10 B
b10 D
15
0"
0P
0T
b10 S
1;
b100 U
1#
#900
b100 ,
0#
#905
07
b11 A
b11 =
05
b100 S
b100000011 <
b100000011 L
0;
b10 U
1#
#910
1"
1P
1T
b100000100 &
b100000100 -
b100000100 F
b100 )
0#
#915
b11 :
b11 E
b10 !
b10 0
b10 N
17
b11 8
b11 B
b11 D
15
0"
0P
0T
b10 S
1;
b100 U
1#
#920
b101 ,
0#
#925
07
b100 A
b100 =
05
b100 S
b100000100 <
b100000100 L
0;
b10 U
1#
#930
1"
1P
1T
b100000101 &
b100000101 -
b100000101 F
b101 )
0#
#935
b100 :
b100 E
b11 !
b11 0
b11 N
17
b100 8
b100 B
b100 D
15
0"
0P
0T
b10 S
1;
b100 U
1#
#940
b110 ,
0#
#945
07
b101 A
b101 =
05
b100 S
b100000101 <
b100000101 L
0;
b10 U
1#
#950
1"
1P
1T
b100000110 &
b100000110 -
b100000110 F
b110 )
0#
#955
b101 :
b101 E
b100 !
b100 0
b100 N
17
b101 8
b101 B
b101 D
15
0"
0P
0T
b10 S
1;
b100 U
1#
#960
b111 ,
0#
#965
07
b110 A
b110 =
05
b100 S
b100000110 <
b100000110 L
0;
b10 U
1#
#970
1"
1P
1T
b100000111 &
b100000111 -
b100000111 F
b111 )
0#
#975
b110 :
b110 E
b101 !
b101 0
b101 N
17
b110 8
b110 B
b110 D
15
0"
0P
0T
b10 S
1;
b100 U
1#
#980
b1000 ,
0#
#985
07
b111 A
b111 =
05
b100 S
b100000111 <
b100000111 L
0;
b10 U
1#
#990
0#
#995
bx :
bx E
b110 !
b110 0
b110 N
b10 S
17
bx 8
bx B
b111 D
15
1;
b100 U
1#
#1000
0#
#1005
03
14
b1110 :
b1110 E
07
b101101 A
b101101 =
05
b100 S
b101101 <
b101101 L
0;
b10 U
b101101 &
b101101 -
b101101 F
1#
#1010
0#
#1015
bx :
bx E
b1110 !
b1110 0
b1110 N
b10 S
17
bx 9
bx >
b101101 @
16
1;
b100 U
1#
#1020
0#
#1025
07
06
b100 S
0;
b10 U
1#
#1030
0#
#1035
bx !
bx 0
bx N
b10 S
17
16
1;
b100 U
1#
#1040
0#
#1045
07
06
b100 S
0;
b10 U
1#
