APB/master.sv
// Code your design here
module AMBA_APB(P_clk,P_rst,P_addr,P_selx,P_enable,P_write,P_wdata,P_ready,P_slverr,P_rdata);
    //input configration 
    input P_clk;
    input P_rst;
    input [31:0]P_addr;
    
    input P_selx;
    input P_enable;
    input P_write;
    input [31:0]P_wdata;
    
    //output configration
    output reg P_ready;
    output reg  P_slverr;
    output reg [31:0]P_rdata;
    //memory decleration
    reg [31:0]mem[31:0];
    //state declaration communication
    parameter [1:0] idle=2'b00;
    parameter [1:0] setup=2'b01;
    parameter [1:0] access=2'b10;
    
    //state declaration of present and next 
    reg [1:0] present_state,next_state;
    
    always @(posedge P_clk) begin
      if(P_rst) present_state <= idle;
      else
        present_state <= next_state;
    end
    always @(*) begin
    //next_state =present_state;
    case (present_state)
      idle:begin
        if (P_selx   & !P_enable) 	
                  next_state = setup;
        P_ready=0;
      end
  
      setup:begin if (!P_enable | !P_selx) 
                          next_state = idle; 
                else begin
                          next_state =access;
                         
                  if(P_write ==1) begin
                    mem[P_addr]= P_wdata;
                    P_ready=1;
                    P_slverr=0;
                     end
                   else begin
                     P_rdata=mem[P_addr];
                     P_ready=1;
                     P_slverr=0;
                   end
                 end
      end
      access :begin
        if (!P_enable | !P_selx) begin
                          next_state = idle;
                          P_ready =0;
               end
      end
      endcase 
  end
endmodule

module tb;
    //input configration 
    reg P_clk;
    reg P_rst;
    reg [31:0]P_addr;
   
    reg P_selx;
    reg P_enable;
    reg P_write;
    reg [31:0]P_wdata;
  
     //output configration
    wire  P_ready;
    wire  P_slverr;
    wire [31:0]P_rdata;
    
    //intantiation of all port
    AMBA_APB  dut1(P_clk,P_rst,P_addr,P_selx,P_enable,P_write,P_wdata,P_ready,P_slverr,P_rdata);
    
    always #5 P_clk=~P_clk;
    
    task initialization;
      begin
        P_clk=0;
        P_rst=0;
        P_addr=0;
        P_selx=0;
        P_enable=0;
        P_write=0;
      end
    endtask
     // task reset.
    task reset;
      begin 
        P_rst=1;
        #10 P_rst=0;
      end
    endtask
    
    
    task write_stimulus;
      begin
        @(posedge P_clk);
        P_selx=1;
        P_write=1;
        P_wdata={$random}%10;
        P_addr=P_addr+1;
       
        @(posedge P_clk);
        P_enable=1;
        P_selx=1;
        @(posedge P_clk);
        P_enable=0;
        P_selx=0;
        
        @(posedge P_clk);
        $strobe ("writing data into memory data_in=%0d adress_in=%0d" , P_wdata,P_addr);
      end
    endtask
        
     task read_stimulus;
      begin
        @(posedge P_clk);
         P_write=0;
         P_selx=1;
         P_enable=0;
        //P_addr=P_addr+1;
        @(posedge P_clk); 
        P_enable=1;
        P_selx=1;
        P_addr<=P_addr+1;
        @(posedge P_clk); 
        P_enable=0;
        P_selx=0;
        
        @(posedge P_clk);
        $strobe("reading data from memory data_out=%0d   address_out=%0d",P_rdata,P_addr);
      end
    endtask
    
     task read_write;
    begin 
      repeat(2) begin 
        write_stimulus;
      end
      #1
      P_addr=0;
      repeat(3) begin 
        read_stimulus;
      end
    end
    endtask
    
      initial begin
      $dumpfile("dump.vcd");
      $dumpvars;
      initialization;//initialize input values
      reset;// generate signal
      read_write;
       #80; $finish;
    end 
endmodule

build/dump.vcd
$date
	Wed Mar 05 12:12:18 2025
$end
$version
	Icarus Verilog
$end
$timescale
	1s
$end
$scope module tb $end
$var wire 1 ! P_slverr $end
$var wire 1 " P_ready $end
$var wire 32 # P_rdata [31:0] $end
$var reg 32 $ P_addr [31:0] $end
$var reg 1 % P_clk $end
$var reg 1 & P_enable $end
$var reg 1 ' P_rst $end
$var reg 1 ( P_selx $end
$var reg 32 ) P_wdata [31:0] $end
$var reg 1 * P_write $end
$scope module dut1 $end
$var wire 32 + P_addr [31:0] $end
$var wire 1 % P_clk $end
$var wire 1 & P_enable $end
$var wire 1 ' P_rst $end
$var wire 1 ( P_selx $end
$var wire 32 , P_wdata [31:0] $end
$var wire 1 * P_write $end
$var parameter 2 - access $end
$var parameter 2 . idle $end
$var parameter 2 / setup $end
$var reg 32 0 P_rdata [31:0] $end
$var reg 1 " P_ready $end
$var reg 1 ! P_slverr $end
$var reg 2 1 next_state [1:0] $end
$var reg 2 2 present_state [1:0] $end
$upscope $end
$scope task initialization $end
$upscope $end
$scope task read_stimulus $end
$upscope $end
$scope task read_write $end
$upscope $end
$scope task reset $end
$upscope $end
$scope task write_stimulus $end
$upscope $end
$upscope $end
$enddefinitions $end
$comment Show the parameter values. $end
$dumpall
b1 /
b0 .
b10 -
$end
#0
$dumpvars
bx 2
bx 1
bx 0
bx ,
b0 +
0*
bx )
0(
1'
0&
0%
b0 $
bx #
x"
x!
$end
#5
0"
b0 2
1%
#10
0%
0'
#15
bx 2
b1 1
b1 $
b1 +
b1000 )
b1000 ,
1*
1(
1%
#20
0%
#25
0!
1"
b10 1
b1 2
1&
1%
#30
0%
#35
0"
b10 2
b0 1
0(
0&
1%
#40
0%
#45
b0 2
1%
#50
0%
#55
b1 1
b10 $
b10 +
b111 )
b111 ,
1(
1%
#60
0%
#65
1"
b10 1
b1 2
1&
1%
#70
0%
#75
0"
b10 2
b0 1
0(
0&
1%
#80
0%
#85
b0 2
1%
#86
b0 $
b0 +
#90
0%
#95
b1 1
1(
0*
1%
#100
0%
#105
1"
b1000 #
b1000 0
b10 1
b1 $
b1 +
b1 2
1&
1%
#110
0%
#115
0"
b10 2
b0 1
0(
0&
1%
#120
0%
#125
b0 2
1%
#130
0%
#135
b1 1
1(
1%
#140
0%
#145
1"
b111 #
b111 0
b10 1
b10 $
b10 +
b1 2
1&
1%
#150
0%
#155
0"
b10 2
b0 1
0(
0&
1%
#160
0%
#165
b0 2
1%
#170
0%
#175
b1 1
1(
1%
#180
0%
#185
1"
bx #
bx 0
b10 1
b11 $
b11 +
b1 2
1&
1%
#190
0%
#195
0"
b10 2
b0 1
0(
0&
1%
#200
0%
#205
b0 2
1%
