System_verilog/mux_2x1.sv
module mux_2x1 (
    input logic a,
    input logic b,
    input logic s,
    output logic y
);
    assign  y = (s ? b : a);
endmodule

module mux_2x1_tb ();
    logic a,b,s,y;
    mux_2x1 dut(a,b,s,y);
    initial begin
        $dumpfile("out.vcd");
        $dumpvars(0, mux_2x1_tb);
        $monitor("a=%0d b=%0d s=%0d y=%0d",a,b,s,y);
        a=0; b=0; s=0; #10;
        a=0; b=1; s=0; #10;
        a=1; b=0; s=0; #10;
        a=1; b=1; s=0; #10;
        a=0; b=0; s=1; #10;
        a=0; b=1; s=1; #10;
        a=1; b=0; s=1; #10;
        a=1; b=1; s=1; #10;
    end
endmodule

build/out.vcd
$date
	Wed Oct 23 18:40:39 2024
$end
$version
	Icarus Verilog
$end
$timescale
	1s
$end
$scope module mux_2x1_tb $end
$var wire 1 ! y $end
$var reg 1 " a $end
$var reg 1 # b $end
$var reg 1 $ s $end
$scope module dut $end
$var wire 1 " a $end
$var wire 1 # b $end
$var wire 1 $ s $end
$var wire 1 ! y $end
$upscope $end
$upscope $end
$enddefinitions $end
$comment Show the parameter values. $end
$dumpall
$end
#0
$dumpvars
0$
0#
0"
0!
$end
#10
1#
#20
1!
0#
1"
#30
1#
#40
0!
1$
0#
0"
#50
1!
1#
#60
0!
0#
1"
#70
1!
1#
