SPI/SPI_PERIFERIAL.sv
module SPI_PERIFERIAL (
    input  logic SCK,         // SPI clock from master
    input  logic CS,           // Slave Select
    input  logic MOSI,         // Master Out, Slave In
    output logic MISO,         // Master In, Slave Out
    input  logic [7:0] data_in,// Data to send
    output logic [7:0] data_out // Received data
);

  reg [2:0] bit_cnt;  // Bit counter
  reg [7:0] shift_reg;  // Shift register for received data

  always @(posedge SCK or posedge CS) begin
    if (CS) begin
      bit_cnt   <= 0;
      shift_reg <= data_in;  // Load new data when CS is high
    end else begin
      shift_reg <= {shift_reg[6:0], 1'b0};  // Shift data out
      MISO      <= shift_reg[7];  // Send MSB first

      data_out  <= {data_out[6:0], MOSI};  // Shift in received data
      bit_cnt   <= bit_cnt + 1;
    end
  end

endmodule

SPI/SPI_CONTROLLER.sv
module SPI_CONTROLLER (
    input  logic clk,
    input  logic rst_n,
    input  logic start,
    input  logic [7:0] in_data,
    input  logic MISO,
    output logic [7:0] out_data,
    output logic MOSI,
    output logic SCK,
    output logic CS
);
  reg [2:0] bit_cnt;
  reg [7:0] shift_reg; 
  reg [7:0] recv_reg; 
  reg       busy;

  always @(posedge clk or negedge rst_n) begin
    if (!rst_n) begin
      out_data <= 0;
      MOSI <= 0;
      SCK <= 0;
      CS <= 1;
      busy <= 0;
      bit_cnt <= 0;
      shift_reg <= 0;
      recv_reg <= 0;
    end else if (start && !busy) begin
        CS <= 0;
        busy <= 1;
        shift_reg <= in_data;
        bit_cnt <= 0;
    end else if (busy) begin
        SCK <= ~SCK;
        if(SCK) begin
            recv_reg <= {recv_reg[6:0], MISO};
            bit_cnt <= bit_cnt + 1;
    
            if (bit_cnt == 7) begin
                out_data <= recv_reg;
                busy <= 0;           
                CS <= 1;             
            end
        end else begin
            MOSI <= shift_reg[7];
            shift_reg <= {shift_reg[6:0], 1'b0};
        end
    end
  end

endmodule

SPI/testbench.sv
`timescale 1ns / 1ps
`include "SPI_CONTROLLER.sv"
`include "SPI_PERIFERIAL.sv"
module spi_tb;
  // Testbench Signals
  reg clk = 0;
  reg rst_n;
  reg start;
  reg [7:0] master_data_in;
  wire [7:0] master_data_out;
  wire SCK, MOSI, MISO, CS;
  reg  [7:0] slave_data_in;
  wire [7:0] slave_data_out;

  // Instantiate SPI Master
  SPI_CONTROLLER uut_master (
      clk,
      rst_n,
      start,
      master_data_in,
      MISO,
      master_data_out,
      MOSI,
      SCK,
      CS
  );

  // Instantiate SPI Slave
  SPI_PERIFERIAL uut_slave (
    SCK,
    CS,
    MOSI,
    MISO,
    slave_data_in,
    slave_data_out
  );

  // Generate Clock
  always #5 clk = ~clk;  // 100MHz clock

  // Test Procedure
  initial begin
    // Initialize signals
    rst_n = 0;
    start = 0;
    master_data_in = 8'hA5;  // Example data
    slave_data_in = 8'h3C;  // Response data from slave
    #20;

    // Release reset
    rst_n = 1;
    #10;

    // Start SPI transaction
    start = 1;
    #10;
    start = 0;

    // Wait for transfer to complete
    #200;

    // Display results
    $display("Master Sent: %h, Slave Received: %h", master_data_in, slave_data_out);
    $display("Slave Sent: %h, Master Received: %h", slave_data_in, master_data_out);

    // End simulation
    #50;
    $finish;
  end

  // Monitor signals
  initial begin
    $dumpfile("spi_tb.vcd");
    $dumpvars(0);
  end

endmodule

build/spi_tb.vcd
$date
	Wed Mar 12 07:29:01 2025
$end
$version
	Icarus Verilog
$end
$timescale
	1ps
$end
$scope module spi_tb $end
$var wire 8 ! slave_data_out [7:0] $end
$var wire 8 " master_data_out [7:0] $end
$var wire 1 # SCK $end
$var wire 1 $ MOSI $end
$var wire 1 % MISO $end
$var wire 1 & CS $end
$var reg 1 ' clk $end
$var reg 8 ( master_data_in [7:0] $end
$var reg 1 ) rst_n $end
$var reg 8 * slave_data_in [7:0] $end
$var reg 1 + start $end
$scope module uut_master $end
$var wire 1 ' clk $end
$var wire 8 , in_data [7:0] $end
$var wire 1 ) rst_n $end
$var wire 1 + start $end
$var wire 1 % MISO $end
$var reg 1 & CS $end
$var reg 1 $ MOSI $end
$var reg 1 # SCK $end
$var reg 3 - bit_cnt [2:0] $end
$var reg 1 . busy $end
$var reg 8 / out_data [7:0] $end
$var reg 8 0 recv_reg [7:0] $end
$var reg 8 1 shift_reg [7:0] $end
$upscope $end
$scope module uut_slave $end
$var wire 1 & CS $end
$var wire 1 $ MOSI $end
$var wire 1 # SCK $end
$var wire 8 2 data_in [7:0] $end
$var reg 1 % MISO $end
$var reg 3 3 bit_cnt [2:0] $end
$var reg 8 4 data_out [7:0] $end
$var reg 8 5 shift_reg [7:0] $end
$upscope $end
$upscope $end
$enddefinitions $end
$comment Show the parameter values. $end
$dumpall
$end
#0
$dumpvars
b111100 5
bx 4
b0 3
b111100 2
b0 1
b0 0
b0 /
0.
b0 -
b10100101 ,
0+
b111100 *
0)
b10100101 (
0'
1&
x%
0$
0#
b0 "
bx !
$end
#5000
1'
#10000
0'
#15000
1'
#20000
0'
1)
#25000
1'
#30000
0'
1+
#35000
b10100101 1
1.
0&
1'
#40000
0'
0+
#45000
b1 3
bx1 !
bx1 4
0%
b1111000 5
b1001010 1
1$
1#
1'
#50000
0'
#55000
b1 -
0#
1'
#60000
0'
#65000
b10 3
bx10 !
bx10 4
b11110000 5
b10010100 1
0$
1#
1'
#70000
0'
#75000
b10 -
0#
1'
#80000
0'
#85000
b11 3
bx101 !
bx101 4
1%
b11100000 5
b101000 1
1$
1#
1'
#90000
0'
#95000
b11 -
b1 0
0#
1'
#100000
0'
#105000
b100 3
bx1010 !
bx1010 4
b11000000 5
b1010000 1
0$
1#
1'
#110000
0'
#115000
b100 -
b11 0
0#
1'
#120000
0'
#125000
b101 3
bx10100 !
bx10100 4
b10000000 5
b10100000 1
1#
1'
#130000
0'
#135000
b101 -
b111 0
0#
1'
#140000
0'
#145000
b110 3
bx101001 !
bx101001 4
b0 5
b1000000 1
1$
1#
1'
#150000
0'
#155000
b110 -
b1111 0
0#
1'
#160000
0'
#165000
b111 3
bx1010010 !
bx1010010 4
0%
b10000000 1
0$
1#
1'
#170000
0'
#175000
b111 -
b11110 0
0#
1'
#180000
0'
#185000
b0 3
b10100101 !
b10100101 4
b0 1
1$
1#
1'
#190000
0'
#195000
b111100 5
1&
0.
b11110 "
b11110 /
b0 -
b111100 0
0#
1'
